[
          {
                    "type": "reading",
                    "id": "reading8",
                    "title": "مفاهيم تصميم التعليم وتقنيته",
                    "content": "نماذج تصميم التعليم:\n1. نموذج جانية وبرجز\n2. نموذج ديك وكاري\n3. المنحى المنظومي\n4. نموذج كمب\n\nافتراضات نجاح تصميم التعليم:\n1. فعالاً (يسهل تعلم المتعلم للعلم والمهارات)\n2. كافياً (يتطلب أقل فترة زمنية ممكنة للتعلم)\n3. جذاباً (يشجع المتعلم على التعلم وتحقيق أهداف التدريس)\n4. ليس المدرس الوسيلة الوحيدة التي يتعلم منها المتعلم\n5. هناك قواعد عامة للتدريس يمكن تطبيقها على كل الأعمار\n6. تقويم المتعلمين يجب أن يكون وفقاً لأهداف التدريس\n7. أن تكون هناك علاقة قوية بين الأهداف ونشاطات التعلم والتقويم\n8. أن يكون الطالب محور العملية التعليمية\n9. التعليم المتميز هو الذي يركز على تعلم المهارات أكثر من التركيز على المعلومات\n\nأبعاد تقنية التعليم:\n1. الوسائل والمعدات\n2. المحتوى التعليمي\n3. الأداء التعليمي\n\nمعادلة النجاح لتقنية التعليم:\nوسيلة تعلم وتعليم مناسبة + محتوى مناسب كماً ونوعاً + أداء تعليمي فعال + أداء المتعلم وأداء المعلم = تقنية تعليم ناجحة\n\nمراحل تصميم التعليم:\nأولاً: مرحلة التحليل\nثانياً: مرحلة وضع الاستراتيجيات\nثالثاً: مرحلة التقويم"
          },
          {
                    "type": "question",
                    "id": 20,
                    "question": "من نماذج تصميم التعليم:",
                    "options": [
                              "أ- نموذج جانية وبرجز",
                              "ب- نموذج ديك وكاري",
                              "ج- المنحى المنظومي",
                              "د- جميع ما سبق"
                    ],
                    "correctAnswer": 3,
                    "relatedReading": "reading8"
          },
          {
                    "type": "question",
                    "id": 21,
                    "question": "من افتراضات نجاح تصميم التعليم:",
                    "options": [
                              "أ- فعالاً",
                              "ب- كافياً",
                              "ج- جذاباً",
                              "د- جميع ما سبق"
                    ],
                    "correctAnswer": 3,
                    "relatedReading": "reading8"
          },
          {
                    "type": "question",
                    "id": 22,
                    "question": "أبعاد تقنية التعليم:",
                    "options": [
                              "أ- المحتوى التعليمي",
                              "ب- الأداء التعليمي",
                              "ج- الوسائل والمعدات",
                              "د- جميع ما سبق"
                    ],
                    "correctAnswer": 3,
                    "relatedReading": "reading8"
          },
          {
                    "type": "question",
                    "id": 23,
                    "question": "معادلة نجاح تقنية التعليم:",
                    "options": [
                              "أ- وسيلة تعلم وتعليم مناسبة",
                              "ب- محتوى مناسب كماً ونوعاً",
                              "ج- أداء تعليمي فعال للمعلم والمتعلم",
                              "د- جميع ما سبق"
                    ],
                    "correctAnswer": 3,
                    "relatedReading": "reading8"
          },
          {
                    "type": "question",
                    "id": 24,
                    "question": "مراحل تصميم التعلم:",
                    "options": [
                              "أ- مرحلة التحليل",
                              "ب- مرحلة وضع الاستراتيجيات",
                              "ج- مرحلة التقويم",
                              "د- جميع ما سبق"
                    ],
                    "correctAnswer": 3,
                    "relatedReading": "reading8"
          }
]